tiled_export/__init__.py
tiled_export/_version.py
tiled_export/catalog.py
tiled_export/export.py
tiled_export/py.typed
tiled_export-0.3.dist-info/licenses/AUTHORS.rst
tiled_export-0.3.dist-info/licenses/LICENSE
tiled_export-0.3.dist-info/METADATA
tiled_export-0.3.dist-info/WHEEL
tiled_export-0.3.dist-info/entry_points.txt
tiled_export-0.3.dist-info/top_level.txt
tiled_export-0.3.dist-info/RECORD
